pyfonybundles/Bundle.py
pyfonybundles/BundleManager.py
pyfonybundles/loader/entry_points_reader.py
pyfonybundles/loader/pyfony_bundles_loader.py
pyfonybundles/loader/pyfony_bundles_loader_mocks.py
pyfonybundles/loader/pyfony_bundles_loader_test.py
pyfonybundles/loader/pyproject_reader.py
pyfony_bundles-0.4.4.dist-info/LICENSE
pyfony_bundles-0.4.4.dist-info/WHEEL
pyfony_bundles-0.4.4.dist-info/METADATA
pyfony_bundles-0.4.4.dist-info/RECORD
