Metadata-Version: 2.1
Name: pyfony-bundles
Version: 0.4.4
Summary: Pyfony Framework bundles base package
Home-page: https://github.com/pyfony/pyfony-bundles
License: MIT
Author: Jiri Koutny
Author-email: jiri.koutny@datasentics.com
Requires-Python: >=3.7,<4.0
Classifier: License :: OSI Approved :: MIT License
Classifier: Operating System :: OS Independent
Classifier: Programming Language :: Python :: 3
Classifier: Programming Language :: Python :: 3.7
Classifier: Programming Language :: Python :: 3.8
Classifier: Programming Language :: Python :: 3.9
Requires-Dist: importlib-metadata (>=3.3)
Requires-Dist: injecta (>=0.10.0,<0.11.0)
Requires-Dist: python-box
Requires-Dist: tomlkit (>=0.5.8,<1.0.0)
Project-URL: Repository, https://github.com/pyfony/pyfony-bundles
